dscan/__init__.py
dscan/cli.py
dscan/dscan.py
dscan-0.1.6.dist-info/entry_points.txt
dscan-0.1.6.dist-info/LICENSE
dscan-0.1.6.dist-info/WHEEL
dscan-0.1.6.dist-info/METADATA
dscan-0.1.6.dist-info/RECORD
