Metadata-Version: 2.1
Name: dscan
Version: 0.1.6
Summary: dscan makes scanning a list of domains for DNS records easy!
Home-page: https://codedin.wales/matthew/dscan
License: MIT
Keywords: dns,scanning,osint,dscan
Author: Matthew Gall
Author-email: me@matthewgall.com
Requires-Python: >=2.7, !=3.0.*, !=3.1.*, !=3.2.*, !=3.3.*, !=3.4.*, !=3.5.*, !=3.6.*
Classifier: License :: OSI Approved :: MIT License
Classifier: Programming Language :: Python :: 2
Classifier: Programming Language :: Python :: 2.7
Classifier: Programming Language :: Python :: 3
Classifier: Programming Language :: Python :: 3.7
Requires-Dist: dnslib (>=0.9.10,<0.10.0)
Requires-Dist: requests (>=2.22,<3.0)
Requires-Dist: toml (>=0.9,<0.10)
Project-URL: Repository, https://codedin.wales/matthew/dscan
